{"max_timesteps": 1000000.0, "noise_clip": 0.5, "folder": "./results/", "discount": 0.99, "expl_noise": 0.1, "trust_critic_weight": 0.01, "use_baseline_in_target": true, "save_models": "True", "ent_weight": 0.01, "use_critic_regularizer": true, "policy_noise": 0.2, "tau": 0.005, "start_timesteps": 10000, "policy_freq": 2, "use_logger": true, "use_value_baseline": true, "diversity_expl": true, "use_regularization_loss": true, "use_dueling": true, "trust_actor_weight": 0.01, "env_name": "InvertedPendulum-v2", "seed": 0, "eval_freq": 5000.0, "policy_name": "DDPGq", "use_log_prob_in_policy": true, "use_actor_regularizer": true, "batch_size": 100}